entense/__init__.py
entense/const.py
entense/data.py
entense-0.0.0.dev0.dist-info/LICENSE
entense-0.0.0.dev0.dist-info/METADATA
entense-0.0.0.dev0.dist-info/WHEEL
entense-0.0.0.dev0.dist-info/top_level.txt
entense-0.0.0.dev0.dist-info/RECORD
