Metadata-Version: 2.1
Name: entense
Version: 0.0.0.dev0
Summary: Data-to-tensor workflows for functional neuroimaging data
Author-email: Rastko Ciric <rastko@stanford.edu>
Maintainer-email: Rastko Ciric <rastko@stanford.edu>
License: Apache License
Project-URL: Homepage, https://github.com/hypercoil/entense
Classifier: Programming Language :: Python :: 3
Classifier: License :: OSI Approved :: Apache Software License
Classifier: Operating System :: POSIX :: Linux
Classifier: Operating System :: MacOS :: MacOS X
Requires-Python: >=3.10
License-File: LICENSE
Requires-Dist: conveyant
Requires-Dist: datalad
Requires-Dist: nibabel
Requires-Dist: numpy
Requires-Dist: pandas
Requires-Dist: scipy
Requires-Dist: lytemaps
Requires-Dist: templateflow
Requires-Dist: tensorflow
Requires-Dist: hypercoil
Requires-Dist: pydra
